{
  "MaHocVien": null,
  "CCCD": null,
  "NgayCapCCCD": null,
  "NoiCapCCCD": null,
  "SoDu": null,
  "Ho": null,
  "Ten":  null,
  "TenDayDu": null,
  "Tuoi": null,
  "GioiTinh": null,
  "NgaySinh": null,
  "DCThuongTru": null,
  "DanToc": null,
  "Tinh": null,
  "Huyen": null,
  "DonVi": null,
  "TinhTrangHN": null,
  "TienAn": null,
  "TienSu": null,
  "TrinhDo": null,
  "ViecLam": null,
  "TonGiao": null,
  "HinhAnh": null,
  "NamSudung": null,
  "HinhThucSuDung": null,
  "TinhTrangNghien": null,
  "LoaiMaTuySD": null,
  "DienThoai": null,
  "DieuTriARV": null,
  "LyDoGiam": null,
  "CoQuanBanGiao": null,
  "ThanhPhanGiaDinh": null,
  "CoQuanXacDinhTinhTrangNghien": null,
  "TuoiLanDauSuDung": null,
  "TuoiLanDauTiemChich": null,
  "TongThoiGianSuDung": null,
  "SoNgayLanSuDung": null,
  "NguyenNhanTaiNghien": null,
  "ThanhPhanBanThan": null,
  "TinhTrangViecLam": null,
  "TronNhapLai": null,
  "NhapMoi": null,
  "GhiChu" :null,
  "deleted": 0
}